{"url": "https://yandex.com/news/rubric/politics?from=index", "creationDate": "2019-10-06", "articles": [{"tittle": "Путин признался в отсутствии интереса к положению Зеленского"}, {"tittle": "Володин назвал циничной провокацией допрос депутата Госдумы в США"}, {"tittle": "В Киеве митингуют против формулы Штайнмайера"}, {"tittle": "Умер вице-спикер Совфеда Евгений Бушмин"}, {"tittle": "Песков рассказал о поездке Путина в тайгу накануне дня рождения"}, {"tittle": "Россия поставила ЦАР автоматы Калашникова и винтовки Мосина"}, {"tittle": "Доклад датского премьера вызвал истерический хохот в парламенте"}, {"tittle": "ABC: второй разведчик рассказал о деталях разговора Трампа с Зеленским"}, {"tittle": "Турция начала стягивать войска к границе с Сирией"}, {"tittle": "В Испании заявили о смене ролей России и США в мировой политике"}, {"tittle": "Украинцы проявили массовый интерес к капитуляции"}, {"tittle": "Журналисты из России попали под обстрел в ДНР"}, {"tittle": "На Украине построенный на деньги США корабль окрестили «бронешлюпкой»"}, {"tittle": "Медведев исключил оказание безвозвратной помощи Кубе"}, {"tittle": "Зеленский захотел вернуться на сцену"}, {"tittle": "Командующий КСИР предрек США крах из-за отсутствия стратегии"}, {"tittle": "Силовики обстреляли школы и дачи в Горловке, сообщили местные власти"}, {"tittle": "В Сети украинские военные извинились, что «не сдохли» в Донбассе"}, {"tittle": "В Польше поклонника бандеровцев заставили съесть красно-черный флажок"}, {"tittle": "В ВКС рассказали о реакции России на возможный ядерный удар"}, {"tittle": "Зеленский ответил за заявления о давлении со стороны Трампа"}, {"tittle": "Представители Киева посетят Донбасс на следующей неделе"}, {"tittle": "Авиация НАТО опубликовала снимок Су-34 в рамке прицела"}, {"tittle": "Украинский посол в Нидерландах ушел от ответа после вопроса о MH17"}, {"tittle": "Власти Дании сняли политические возражения по «Северному потоку — 2»"}, {"tittle": "В КНДР заявили о провале переговоров с США"}, {"tittle": "Украинцы требуют обнародовать стенограммы переговоров Порошенко с США"}, {"tittle": "Российскую журналистку Юлию Юзик задержали в Тегеране"}, {"tittle": "Лукашевич оценил перспективы проведения саммита в нормандском формате"}]}